huffman/__init__.py
huffman/huffman.py
huffman_algorithm-1.0.1.dist-info/METADATA
huffman_algorithm-1.0.1.dist-info/WHEEL
huffman_algorithm-1.0.1.dist-info/licenses/LICENSE
huffman_algorithm-1.0.1.dist-info/RECORD
