Metadata-Version: 2.1
Name: huffman-algorithm
Version: 1.0.1
Summary: Python Huffman Algorithm Implementation
Project-URL: Homepage, https://www.github.com/ugo-brocard/huffman-algorithm
Author-email: Ugo Brocard <ugo.brocard.official+contact@gmail.com>
License-File: LICENSE
Classifier: License :: OSI Approved :: MIT License
Classifier: Operating System :: OS Independent
Classifier: Programming Language :: Python :: 3
Requires-Python: >=3.12
